mypackage/__init__.py
mypackage/mypackage.py
PyCon2019-0.0.3.post1.dist-info/METADATA
PyCon2019-0.0.3.post1.dist-info/WHEEL
PyCon2019-0.0.3.post1.dist-info/top_level.txt
PyCon2019-0.0.3.post1.dist-info/RECORD
