Metadata-Version: 2.1
Name: PyCon2019
Version: 0.0.3.post1
Summary: My first package
Home-page: https://github.com/crwilcox/my-pypi-package
Author: Chris Wilcox
Author-email: pypi@crwilcox.com
License: Apache 2.0
Platform: UNKNOWN
Classifier: Development Status :: 3 - Alpha
Classifier: License :: OSI Approved :: Apache Software License
Classifier: Programming Language :: Python
Classifier: Programming Language :: Python :: 3
Classifier: Programming Language :: Python :: 3.5
Classifier: Programming Language :: Python :: 3.6
Classifier: Programming Language :: Python :: 3.7
Classifier: Operating System :: OS Independent
Classifier: Topic :: Utilities
